{
  "conditions": [
    {
      "condition": "minecraft:alternative",
      "terms": [
        {
          "condition": "forge:loot_table_id",
          "loot_table_id": "minecraft:entities/cave_spider"
        },
        {
          "condition": "forge:loot_table_id",
          "loot_table_id": "minecraft:entities/creeper"
        },
        {
          "condition": "forge:loot_table_id",
          "loot_table_id": "minecraft:entities/enderman"
        },
        {
          "condition": "forge:loot_table_id",
          "loot_table_id": "minecraft:entities/evoker"
        },
        {
          "condition": "forge:loot_table_id",
          "loot_table_id": "minecraft:entities/illusioner"
        },
        {
          "condition": "forge:loot_table_id",
          "loot_table_id": "minecraft:entities/magma_cube"
        },
        {
          "condition": "forge:loot_table_id",
          "loot_table_id": "minecraft:entities/phantom"
        },
        {
          "condition": "forge:loot_table_id",
          "loot_table_id": "minecraft:entities/piglin"
        },
        {
          "condition": "forge:loot_table_id",
          "loot_table_id": "minecraft:entities/pillager"
        },
        {
          "condition": "forge:loot_table_id",
          "loot_table_id": "minecraft:entities/slime"
        },
        {
          "condition": "forge:loot_table_id",
          "loot_table_id": "minecraft:entities/spider"
        },
        {
          "condition": "forge:loot_table_id",
          "loot_table_id": "minecraft:entities/vex"
        },
        {
          "condition": "forge:loot_table_id",
          "loot_table_id": "minecraft:entities/witch"
        },
        {
          "condition": "forge:loot_table_id",
          "loot_table_id": "minecraft:entities/zombified_piglin"
        }
      ]
    }
  ],
  "count": 1,
  "rarity": "common",
  "chance": 0.1,
  "lootTable": "gealdorcraft:entities/general",
  "type": "gealdorcraft:loot_modifier_by_loot_table"
}